[
  {
    "design_id": "r9_c4_long_helix_capper_s0",
    "backbone_id": "r9_c4_long_helix_capper",
    "params": {
      "topology": "long_helix_capper",
      "standoff_A": 7.541754854314685,
      "mpnn_temperature": 0.1,
      "hotspot_fraction": 0.5283788235581108
    },
    "sequence": "EEEKKKKEEEKKKKEEEEKKKEEEKKKEEEEKKKKEEEEKKKEEEEKEKKKKEEEKKKKEEKELK",
    "mpnn_score": 1.0137,
    "geometric": {
      "n_clashes": 11,
      "n_contacts": 215,
      "n_hbond_candidates": 12,
      "clash_score": 0.0338,
      "packing_density_sc_proxy": 0.0764,
      "mean_contacts_per_atom": 0.662
    },
    "esm_plausibility": 0.9475,
    "developability": {
      "max_own_aggregation_score": 0.0104,
      "percentile_vs_reference_windows": 12.5,
      "max_allowed_percentile": 40,
      "scoring_basis": "exposed_windows_only",
      "n_cysteines": 0,
      "cysteine_check_passed": true,
      "developability_passed": true
    },
    "hydrophobic_core_consistency": {
      "n_residues": 65,
      "pearson_r": 0.0396,
      "pearson_p": 0.754284,
      "well_packed": false,
      "rel_sasa_by_resid": {
        "1": 0.85,
        "2": 0.6662,
        "3": 0.644,
        "4": 0.7248,
        "5": 0.6066,
        "6": 0.605,
        "7": 0.5733,
        "8": 0.5184,
        "9": 0.5178,
        "10": 0.4964,
        "11": 0.6805,
        "12": 0.5999,
        "13": 0.603,
        "14": 0.5916,
        "15": 0.5107,
        "16": 0.5174,
        "17": 0.5179,
        "18": 0.6271,
        "19": 0.5865,
        "20": 0.6042,
        "21": 0.5946,
        "22": 0.5123,
        "23": 0.5173,
        "24": 0.5516,
        "25": 0.6405,
        "26": 0.6002,
        "27": 0.607,
        "28": 0.5047,
        "29": 0.517,
        "30": 0.5209,
        "31": 0.5628,
        "32": 0.6358,
        "33": 0.6078,
        "34": 0.6068,
        "35": 0.5914,
        "36": 0.5117,
        "37": 0.5162,
        "38": 0.5183,
        "39": 0.6267,
        "40": 0.5826,
        "41": 0.5971,
        "42": 0.6176,
        "43": 0.5022,
        "44": 0.5762,
        "45": 0.505,
        "46": 0.5678,
        "47": 0.6297,
        "48": 0.5604,
        "49": 0.6354,
        "50": 0.5745,
        "51": 0.6499,
        "52": 0.5649,
        "53": 0.5152,
        "54": 0.5202,
        "55": 0.4987,
        "56": 0.6839,
        "57": 0.5983,
        "58": 0.5831,
        "59": 0.6363,
        "60": 0.5249,
        "61": 0.4251,
        "62": 0.7111,
        "63": 0.7499,
        "64": 0.6784,
        "65": 0.8845
      }
    },
    "chemical_complementarity": {
      "n_chemical_contacts": 51,
      "hydrophobic_complementarity": 4.3282,
      "charge_complementarity": 0.098
    },
    "composite_score": 0.4676,
    "selectivity_margin": 0.0298,
    "individually_significant": false
  },
  {
    "design_id": "r9_c4_long_helix_capper_s3",
    "backbone_id": "r9_c4_long_helix_capper",
    "params": {
      "topology": "long_helix_capper",
      "standoff_A": 7.541754854314685,
      "mpnn_temperature": 0.1,
      "hotspot_fraction": 0.5283788235581108
    },
    "sequence": "EEEKKKLEEEEKKKEEEKEKEEEEEEKKEEEEKEKEEEEEEKKEEEKKKEEEKKKEEEKKKKELE",
    "mpnn_score": 1.0478,
    "geometric": {
      "n_clashes": 11,
      "n_contacts": 215,
      "n_hbond_candidates": 12,
      "clash_score": 0.0338,
      "packing_density_sc_proxy": 0.0764,
      "mean_contacts_per_atom": 0.662
    },
    "esm_plausibility": 0.942,
    "developability": {
      "max_own_aggregation_score": 0.0546,
      "percentile_vs_reference_windows": 12.5,
      "max_allowed_percentile": 40,
      "scoring_basis": "exposed_windows_only",
      "n_cysteines": 0,
      "cysteine_check_passed": true,
      "developability_passed": true
    },
    "hydrophobic_core_consistency": {
      "n_residues": 65,
      "pearson_r": -0.0653,
      "pearson_p": 0.605324,
      "well_packed": false,
      "rel_sasa_by_resid": {
        "1": 0.8491,
        "2": 0.6665,
        "3": 0.6711,
        "4": 0.6316,
        "5": 0.6079,
        "6": 0.6234,
        "7": 0.5083,
        "8": 0.4973,
        "9": 0.5168,
        "10": 0.6012,
        "11": 0.6299,
        "12": 0.5887,
        "13": 0.6005,
        "14": 0.5972,
        "15": 0.5759,
        "16": 0.5061,
        "17": 0.5595,
        "18": 0.6547,
        "19": 0.6201,
        "20": 0.6068,
        "21": 0.5638,
        "22": 0.643,
        "23": 0.5049,
        "24": 0.5835,
        "25": 0.6481,
        "26": 0.6224,
        "27": 0.5865,
        "28": 0.6132,
        "29": 0.5756,
        "30": 0.5792,
        "31": 0.5038,
        "32": 0.6308,
        "33": 0.6072,
        "34": 0.6179,
        "35": 0.6042,
        "36": 0.5691,
        "37": 0.6405,
        "38": 0.5068,
        "39": 0.5866,
        "40": 0.6475,
        "41": 0.6187,
        "42": 0.5907,
        "43": 0.5974,
        "44": 0.5802,
        "45": 0.5094,
        "46": 0.5593,
        "47": 0.6423,
        "48": 0.6036,
        "49": 0.6007,
        "50": 0.5084,
        "51": 0.5152,
        "52": 0.5566,
        "53": 0.64,
        "54": 0.6034,
        "55": 0.5971,
        "56": 0.5074,
        "57": 0.5127,
        "58": 0.4968,
        "59": 0.6893,
        "60": 0.586,
        "61": 0.5493,
        "62": 0.6223,
        "63": 0.681,
        "64": 0.6528,
        "65": 0.8264
      }
    },
    "chemical_complementarity": {
      "n_chemical_contacts": 51,
      "hydrophobic_complementarity": 4.3024,
      "charge_complementarity": 0.1765
    },
    "composite_score": 0.476,
    "selectivity_margin": 0.0294,
    "individually_significant": false
  },
  {
    "design_id": "r0_c1_scaffold_engrailed_hd_s3",
    "backbone_id": "r0_c1_scaffold_engrailed_hd",
    "params": {
      "topology": "scaffold_engrailed_hd",
      "standoff_A": 13.28851444221563,
      "mpnn_temperature": 0.1,
      "hotspot_fraction": 0.7251929689477836
    },
    "sequence": "KKPIKLTPEQKKALDKRFAENPILSPEELKKLSKELGLPEEQIRQWFKERRKKA",
    "mpnn_score": 1.105,
    "geometric": {
      "n_clashes": 31,
      "n_contacts": 356,
      "n_hbond_candidates": 17,
      "clash_score": 0.1148,
      "packing_density_sc_proxy": 0.1415,
      "mean_contacts_per_atom": 1.319
    },
    "esm_plausibility": 0.9361,
    "developability": {
      "max_own_aggregation_score": 0.5932,
      "percentile_vs_reference_windows": 37.5,
      "max_allowed_percentile": 40,
      "scoring_basis": "exposed_windows_only",
      "n_cysteines": 0,
      "cysteine_check_passed": true,
      "developability_passed": true
    },
    "hydrophobic_core_consistency": {
      "n_residues": 54,
      "pearson_r": -0.4473,
      "pearson_p": 0.000695,
      "well_packed": true,
      "rel_sasa_by_resid": {
        "1": 0.714,
        "2": 0.8509,
        "3": 0.3419,
        "4": 0.5464,
        "5": 0.6659,
        "6": 0.1905,
        "7": 0.5189,
        "8": 0.521,
        "9": 0.6552,
        "10": 0.0632,
        "11": 0.268,
        "12": 0.5888,
        "13": 0.3979,
        "14": 0.0377,
        "15": 0.2085,
        "16": 0.637,
        "17": 0.3468,
        "18": 0.1648,
        "19": 0.5031,
        "20": 0.633,
        "21": 0.5047,
        "22": 0.2923,
        "23": 0.5563,
        "24": 0.0717,
        "25": 0.5131,
        "26": 0.469,
        "27": 0.5542,
        "28": 0.445,
        "29": 0.0146,
        "30": 0.3501,
        "31": 0.405,
        "32": 0.0354,
        "33": 0.0207,
        "34": 0.564,
        "35": 0.515,
        "36": 0.2641,
        "37": 0.529,
        "38": 0.205,
        "39": 0.4077,
        "40": 0.1521,
        "41": 0.3914,
        "42": 0.0915,
        "43": 0.029,
        "44": 0.3947,
        "45": 0.421,
        "46": 0.2303,
        "47": 0.0097,
        "48": 0.4791,
        "49": 0.6225,
        "50": 0.5343,
        "51": 0.3119,
        "52": 0.6618,
        "53": 0.5581,
        "54": 0.8063
      }
    },
    "chemical_complementarity": {
      "n_chemical_contacts": 105,
      "hydrophobic_complementarity": 1.0743,
      "charge_complementarity": -0.0571
    },
    "composite_score": 0.4349,
    "selectivity_margin": 0.0103,
    "individually_significant": false
  },
  {
    "design_id": "r0_c6_helix_hairpin_s1",
    "backbone_id": "r0_c6_helix_hairpin",
    "params": {
      "topology": "helix_hairpin",
      "standoff_A": 14.765584195159226,
      "mpnn_temperature": 0.2,
      "hotspot_fraction": 0.889191748536881
    },
    "sequence": "ELKKALEEIKKELEKEKKKAEEEKKKVLKGGGKGEKEKALKEIKKKLEKAKEKAEKERKKVEEK",
    "mpnn_score": 1.0277,
    "geometric": {
      "n_clashes": 8,
      "n_contacts": 172,
      "n_hbond_candidates": 5,
      "clash_score": 0.025,
      "packing_density_sc_proxy": 0.063,
      "mean_contacts_per_atom": 0.537
    },
    "esm_plausibility": 0.943,
    "developability": {
      "max_own_aggregation_score": 0.4383,
      "percentile_vs_reference_windows": 12.5,
      "max_allowed_percentile": 40,
      "scoring_basis": "exposed_windows_only",
      "n_cysteines": 0,
      "cysteine_check_passed": true,
      "developability_passed": true
    },
    "hydrophobic_core_consistency": {
      "n_residues": 64,
      "pearson_r": -0.631,
      "pearson_p": 0.0,
      "well_packed": true,
      "rel_sasa_by_resid": {
        "1": 0.8629,
        "2": 0.4057,
        "3": 0.6359,
        "4": 0.6848,
        "5": 0.4199,
        "6": 0.0658,
        "7": 0.49,
        "8": 0.587,
        "9": 0.1215,
        "10": 0.4453,
        "11": 0.5654,
        "12": 0.5797,
        "13": 0.1659,
        "14": 0.4361,
        "15": 0.455,
        "16": 0.5638,
        "17": 0.2432,
        "18": 0.3824,
        "19": 0.634,
        "20": 0.1209,
        "21": 0.4194,
        "22": 0.4695,
        "23": 0.4096,
        "24": 0.1656,
        "25": 0.5084,
        "26": 0.6097,
        "27": 0.1226,
        "28": 0.4386,
        "29": 0.7942,
        "30": 0.6096,
        "31": 0.1491,
        "32": 0.0928,
        "33": 0.6383,
        "34": 0.0451,
        "35": 0.7204,
        "36": 0.2493,
        "37": 0.6322,
        "38": 0.5969,
        "39": 0.2964,
        "40": 0.0715,
        "41": 0.5184,
        "42": 0.5307,
        "43": 0.2878,
        "44": 0.3805,
        "45": 0.4661,
        "46": 0.648,
        "47": 0.1519,
        "48": 0.4271,
        "49": 0.5941,
        "50": 0.3264,
        "51": 0.3139,
        "52": 0.5614,
        "53": 0.6795,
        "54": 0.1839,
        "55": 0.3874,
        "56": 0.6226,
        "57": 0.5183,
        "58": 0.2526,
        "59": 0.368,
        "60": 0.5993,
        "61": 0.2189,
        "62": 0.4125,
        "63": 0.7157,
        "64": 0.8832
      }
    },
    "chemical_complementarity": {
      "n_chemical_contacts": 44,
      "hydrophobic_complementarity": 5.0966,
      "charge_complementarity": -0.1591
    },
    "composite_score": 0.5261,
    "selectivity_margin": 0.0099,
    "individually_significant": false
  },
  {
    "design_id": "r0_c6_helix_hairpin_s2",
    "backbone_id": "r0_c6_helix_hairpin",
    "params": {
      "topology": "helix_hairpin",
      "standoff_A": 14.765584195159226,
      "mpnn_temperature": 0.2,
      "hotspot_fraction": 0.889191748536881
    },
    "sequence": "KLEEELKKIEEELKKEKEKAEKEKEKIKKGGGSEAKELALKKIEEELKKAKKKAEEEKEKVKKK",
    "mpnn_score": 1.0252,
    "geometric": {
      "n_clashes": 8,
      "n_contacts": 172,
      "n_hbond_candidates": 5,
      "clash_score": 0.025,
      "packing_density_sc_proxy": 0.063,
      "mean_contacts_per_atom": 0.537
    },
    "esm_plausibility": 0.9436,
    "developability": {
      "max_own_aggregation_score": 0.5409,
      "percentile_vs_reference_windows": 37.5,
      "max_allowed_percentile": 40,
      "scoring_basis": "exposed_windows_only",
      "n_cysteines": 0,
      "cysteine_check_passed": true,
      "developability_passed": true
    },
    "hydrophobic_core_consistency": {
      "n_residues": 64,
      "pearson_r": -0.5345,
      "pearson_p": 5e-06,
      "well_packed": true,
      "rel_sasa_by_resid": {
        "1": 0.8793,
        "2": 0.5085,
        "3": 0.6276,
        "4": 0.6581,
        "5": 0.4278,
        "6": 0.2208,
        "7": 0.536,
        "8": 0.6315,
        "9": 0.0995,
        "10": 0.416,
        "11": 0.3914,
        "12": 0.524,
        "13": 0.1422,
        "14": 0.4795,
        "15": 0.5228,
        "16": 0.5528,
        "17": 0.2647,
        "18": 0.4259,
        "19": 0.6811,
        "20": 0.17,
        "21": 0.5005,
        "22": 0.5,
        "23": 0.4044,
        "24": 0.3319,
        "25": 0.5468,
        "26": 0.5063,
        "27": 0.1924,
        "28": 0.4769,
        "29": 0.811,
        "30": 0.6455,
        "31": 0.2805,
        "32": 0.2092,
        "33": 0.1491,
        "34": 0.3841,
        "35": 0.4166,
        "36": 0.2321,
        "37": 0.4966,
        "38": 0.6668,
        "39": 0.2343,
        "40": 0.1916,
        "41": 0.589,
        "42": 0.5993,
        "43": 0.3409,
        "44": 0.4969,
        "45": 0.5153,
        "46": 0.4597,
        "47": 0.1457,
        "48": 0.5221,
        "49": 0.4726,
        "50": 0.3748,
        "51": 0.3762,
        "52": 0.4886,
        "53": 0.5347,
        "54": 0.0919,
        "55": 0.5471,
        "56": 0.4184,
        "57": 0.3947,
        "58": 0.0778,
        "59": 0.478,
        "60": 0.5391,
        "61": 0.3705,
        "62": 0.5843,
        "63": 0.7858,
        "64": 0.8463
      }
    },
    "chemical_complementarity": {
      "n_chemical_contacts": 44,
      "hydrophobic_complementarity": 5.0548,
      "charge_complementarity": -0.1136
    },
    "composite_score": 0.519,
    "selectivity_margin": 0.0099,
    "individually_significant": false
  },
  {
    "design_id": "r0_c6_helix_hairpin_s0",
    "backbone_id": "r0_c6_helix_hairpin",
    "params": {
      "topology": "helix_hairpin",
      "standoff_A": 14.765584195159226,
      "mpnn_temperature": 0.2,
      "hotspot_fraction": 0.889191748536881
    },
    "sequence": "ALEKALEAIKKELEKAKKEAKEKVEKIKKGGGGGEKEKALEKIKKELEEAKKEAKKKVEEAKAK",
    "mpnn_score": 0.9996,
    "geometric": {
      "n_clashes": 8,
      "n_contacts": 172,
      "n_hbond_candidates": 5,
      "clash_score": 0.025,
      "packing_density_sc_proxy": 0.063,
      "mean_contacts_per_atom": 0.537
    },
    "esm_plausibility": 0.9443,
    "developability": {
      "max_own_aggregation_score": 0.4663,
      "percentile_vs_reference_windows": 25.0,
      "max_allowed_percentile": 40,
      "scoring_basis": "exposed_windows_only",
      "n_cysteines": 0,
      "cysteine_check_passed": true,
      "developability_passed": true
    },
    "hydrophobic_core_consistency": {
      "n_residues": 64,
      "pearson_r": -0.5513,
      "pearson_p": 2e-06,
      "well_packed": true,
      "rel_sasa_by_resid": {
        "1": 0.967,
        "2": 0.6473,
        "3": 0.4621,
        "4": 0.6437,
        "5": 0.5546,
        "6": 0.2748,
        "7": 0.5162,
        "8": 0.4046,
        "9": 0.2907,
        "10": 0.4382,
        "11": 0.4287,
        "12": 0.5102,
        "13": 0.1314,
        "14": 0.6024,
        "15": 0.6377,
        "16": 0.3135,
        "17": 0.1775,
        "18": 0.6326,
        "19": 0.4589,
        "20": 0.0751,
        "21": 0.4894,
        "22": 0.5782,
        "23": 0.5179,
        "24": 0.1246,
        "25": 0.532,
        "26": 0.6212,
        "27": 0.0686,
        "28": 0.3917,
        "29": 0.658,
        "30": 0.5657,
        "31": 0.2784,
        "32": 0.1923,
        "33": 0.1937,
        "34": 0.1131,
        "35": 0.7291,
        "36": 0.3704,
        "37": 0.5967,
        "38": 0.5726,
        "39": 0.2935,
        "40": 0.1778,
        "41": 0.558,
        "42": 0.6265,
        "43": 0.235,
        "44": 0.4492,
        "45": 0.497,
        "46": 0.5777,
        "47": 0.0892,
        "48": 0.3973,
        "49": 0.6189,
        "50": 0.4401,
        "51": 0.3455,
        "52": 0.5362,
        "53": 0.5125,
        "54": 0.0656,
        "55": 0.4042,
        "56": 0.5589,
        "57": 0.5342,
        "58": 0.2003,
        "59": 0.4577,
        "60": 0.466,
        "61": 0.3875,
        "62": 0.6215,
        "63": 0.6191,
        "64": 0.9071
      }
    },
    "chemical_complementarity": {
      "n_chemical_contacts": 44,
      "hydrophobic_complementarity": 3.8936,
      "charge_complementarity": -0.0909
    },
    "composite_score": 0.4976,
    "selectivity_margin": 0.0087,
    "individually_significant": false
  },
  {
    "design_id": "r0_c6_helix_hairpin_s3",
    "backbone_id": "r0_c6_helix_hairpin",
    "params": {
      "topology": "helix_hairpin",
      "standoff_A": 14.765584195159226,
      "mpnn_temperature": 0.2,
      "hotspot_fraction": 0.889191748536881
    },
    "sequence": "EKEKELEKIKKELKKAKEEAEKKLKEIEKGGGKKEKKEAIEKIKKKLEEKEKEAEEKKKKVEEK",
    "mpnn_score": 1.0158,
    "geometric": {
      "n_clashes": 8,
      "n_contacts": 172,
      "n_hbond_candidates": 5,
      "clash_score": 0.025,
      "packing_density_sc_proxy": 0.063,
      "mean_contacts_per_atom": 0.537
    },
    "esm_plausibility": 0.9443,
    "developability": {
      "max_own_aggregation_score": 0.3447,
      "percentile_vs_reference_windows": 12.5,
      "max_allowed_percentile": 40,
      "scoring_basis": "exposed_windows_only",
      "n_cysteines": 0,
      "cysteine_check_passed": true,
      "developability_passed": true
    },
    "hydrophobic_core_consistency": {
      "n_residues": 64,
      "pearson_r": -0.7151,
      "pearson_p": 0.0,
      "well_packed": true,
      "rel_sasa_by_resid": {
        "1": 0.7704,
        "2": 0.4953,
        "3": 0.5586,
        "4": 0.5346,
        "5": 0.4102,
        "6": 0.2933,
        "7": 0.479,
        "8": 0.5492,
        "9": 0.1643,
        "10": 0.4341,
        "11": 0.5571,
        "12": 0.6007,
        "13": 0.1261,
        "14": 0.384,
        "15": 0.5529,
        "16": 0.4385,
        "17": 0.4539,
        "18": 0.5239,
        "19": 0.5731,
        "20": 0.121,
        "21": 0.4846,
        "22": 0.4893,
        "23": 0.4889,
        "24": 0.1066,
        "25": 0.5544,
        "26": 0.5799,
        "27": 0.0822,
        "28": 0.4708,
        "29": 0.8081,
        "30": 0.5014,
        "31": 0.2053,
        "32": 0.1422,
        "33": 0.5138,
        "34": 0.4778,
        "35": 0.5865,
        "36": 0.1178,
        "37": 0.657,
        "38": 0.4924,
        "39": 0.1625,
        "40": 0.2294,
        "41": 0.5558,
        "42": 0.4647,
        "43": 0.2355,
        "44": 0.2905,
        "45": 0.6613,
        "46": 0.5462,
        "47": 0.1735,
        "48": 0.4913,
        "49": 0.4919,
        "50": 0.6056,
        "51": 0.2811,
        "52": 0.4918,
        "53": 0.5784,
        "54": 0.1318,
        "55": 0.5605,
        "56": 0.4515,
        "57": 0.5839,
        "58": 0.1945,
        "59": 0.5985,
        "60": 0.5817,
        "61": 0.3369,
        "62": 0.5075,
        "63": 0.6598,
        "64": 0.7962
      }
    },
    "chemical_complementarity": {
      "n_chemical_contacts": 44,
      "hydrophobic_complementarity": 3.7668,
      "charge_complementarity": -0.0455
    },
    "composite_score": 0.5082,
    "selectivity_margin": 0.0082,
    "individually_significant": false
  },
  {
    "design_id": "r3_c3_helix_hairpin_s1",
    "backbone_id": "r3_c3_helix_hairpin",
    "params": {
      "topology": "helix_hairpin",
      "standoff_A": 10.146415069594463,
      "mpnn_temperature": 0.2,
      "hotspot_fraction": 0.84437610637996
    },
    "sequence": "EEALKEFKKKLEEEKKKLEEKIKKIKEERKKGEKKEEIDKELEKEKEEFKKKIEEKKKELEKKL",
    "mpnn_score": 1.1758,
    "geometric": {
      "n_clashes": 31,
      "n_contacts": 363,
      "n_hbond_candidates": 14,
      "clash_score": 0.0969,
      "packing_density_sc_proxy": 0.1242,
      "mean_contacts_per_atom": 1.134
    },
    "esm_plausibility": 0.9428,
    "developability": {
      "max_own_aggregation_score": 0.4512,
      "percentile_vs_reference_windows": 25.0,
      "max_allowed_percentile": 40,
      "scoring_basis": "exposed_windows_only",
      "n_cysteines": 0,
      "cysteine_check_passed": true,
      "developability_passed": true
    },
    "hydrophobic_core_consistency": {
      "n_residues": 64,
      "pearson_r": -0.5034,
      "pearson_p": 2.2e-05,
      "well_packed": true,
      "rel_sasa_by_resid": {
        "1": 0.7523,
        "2": 0.6133,
        "3": 0.6167,
        "4": 0.3222,
        "5": 0.5965,
        "6": 0.5945,
        "7": 0.0961,
        "8": 0.4238,
        "9": 0.6597,
        "10": 0.5838,
        "11": 0.1216,
        "12": 0.4985,
        "13": 0.5281,
        "14": 0.2829,
        "15": 0.3703,
        "16": 0.5654,
        "17": 0.645,
        "18": 0.3659,
        "19": 0.4401,
        "20": 0.5126,
        "21": 0.5531,
        "22": 0.184,
        "23": 0.4798,
        "24": 0.5071,
        "25": 0.3437,
        "26": 0.299,
        "27": 0.5209,
        "28": 0.5718,
        "29": 0.2279,
        "30": 0.5113,
        "31": 0.4814,
        "32": 0.2009,
        "33": 0.4202,
        "34": 0.4724,
        "35": 0.1727,
        "36": 0.6208,
        "37": 0.6125,
        "38": 0.2762,
        "39": 0.1439,
        "40": 0.5918,
        "41": 0.4672,
        "42": 0.2638,
        "43": 0.533,
        "44": 0.5445,
        "45": 0.5068,
        "46": 0.259,
        "47": 0.4974,
        "48": 0.4845,
        "49": 0.3718,
        "50": 0.6504,
        "51": 0.6664,
        "52": 0.5511,
        "53": 0.1949,
        "54": 0.5217,
        "55": 0.5434,
        "56": 0.5274,
        "57": 0.3063,
        "58": 0.5566,
        "59": 0.5749,
        "60": 0.1687,
        "61": 0.6285,
        "62": 0.7358,
        "63": 0.6703,
        "64": 0.7091
      }
    },
    "chemical_complementarity": {
      "n_chemical_contacts": 104,
      "hydrophobic_complementarity": 3.3377,
      "charge_complementarity": -0.0673
    },
    "composite_score": 0.4841,
    "selectivity_margin": 0.0065,
    "individually_significant": false
  },
  {
    "design_id": "r3_c3_helix_hairpin_s0",
    "backbone_id": "r3_c3_helix_hairpin",
    "params": {
      "topology": "helix_hairpin",
      "standoff_A": 10.146415069594463,
      "mpnn_temperature": 0.2,
      "hotspot_fraction": 0.84437610637996
    },
    "sequence": "KEREEKFKKEIKEEEKKEEEELKKIFEELKKEAGLEEKLKEIEERLKKREEERKKKLKKKKEEE",
    "mpnn_score": 1.3225,
    "geometric": {
      "n_clashes": 31,
      "n_contacts": 363,
      "n_hbond_candidates": 14,
      "clash_score": 0.0969,
      "packing_density_sc_proxy": 0.1242,
      "mean_contacts_per_atom": 1.134
    },
    "esm_plausibility": 0.9413,
    "developability": {
      "max_own_aggregation_score": 0.5629,
      "percentile_vs_reference_windows": 37.5,
      "max_allowed_percentile": 40,
      "scoring_basis": "exposed_windows_only",
      "n_cysteines": 0,
      "cysteine_check_passed": true,
      "developability_passed": true
    },
    "hydrophobic_core_consistency": {
      "n_residues": 64,
      "pearson_r": -0.4425,
      "pearson_p": 0.000251,
      "well_packed": true,
      "rel_sasa_by_resid": {
        "1": 0.8914,
        "2": 0.5713,
        "3": 0.5003,
        "4": 0.2318,
        "5": 0.4018,
        "6": 0.4605,
        "7": 0.1969,
        "8": 0.3091,
        "9": 0.5274,
        "10": 0.5239,
        "11": 0.1299,
        "12": 0.4176,
        "13": 0.4865,
        "14": 0.3837,
        "15": 0.5031,
        "16": 0.5474,
        "17": 0.5447,
        "18": 0.1781,
        "19": 0.5709,
        "20": 0.5433,
        "21": 0.3084,
        "22": 0.1901,
        "23": 0.6126,
        "24": 0.6259,
        "25": 0.5201,
        "26": 0.4505,
        "27": 0.5585,
        "28": 0.6205,
        "29": 0.2441,
        "30": 0.5277,
        "31": 0.3766,
        "32": 0.4728,
        "33": 0.2162,
        "34": 0.2266,
        "35": 0.5856,
        "36": 0.4753,
        "37": 0.5174,
        "38": 0.6039,
        "39": 0.3467,
        "40": 0.5171,
        "41": 0.4631,
        "42": 0.3383,
        "43": 0.5686,
        "44": 0.4636,
        "45": 0.4912,
        "46": 0.3799,
        "47": 0.536,
        "48": 0.5516,
        "49": 0.3115,
        "50": 0.4046,
        "51": 0.6129,
        "52": 0.3339,
        "53": 0.2815,
        "54": 0.5132,
        "55": 0.6025,
        "56": 0.4384,
        "57": 0.1974,
        "58": 0.5872,
        "59": 0.545,
        "60": 0.1026,
        "61": 0.5671,
        "62": 0.6887,
        "63": 0.6511,
        "64": 0.6795
      }
    },
    "chemical_complementarity": {
      "n_chemical_contacts": 104,
      "hydrophobic_complementarity": 3.4096,
      "charge_complementarity": -0.0192
    },
    "composite_score": 0.4818,
    "selectivity_margin": 0.0062,
    "individually_significant": false
  },
  {
    "design_id": "r2_c2_scaffold_protA_bdomain_s2",
    "backbone_id": "r2_c2_scaffold_protA_bdomain",
    "params": {
      "topology": "scaffold_protA_bdomain",
      "standoff_A": 11.47365728596331,
      "mpnn_temperature": 0.15,
      "hotspot_fraction": 0.5154089172839698
    },
    "sequence": "RRLRRPRRGARRGLREARTLPALPREEVEALLREAEEDPSGARRRLREVRRLARERAPPA",
    "mpnn_score": 1.2677,
    "geometric": {
      "n_clashes": 76,
      "n_contacts": 682,
      "n_hbond_candidates": 27,
      "clash_score": 0.2533,
      "packing_density_sc_proxy": 0.2213,
      "mean_contacts_per_atom": 2.273
    },
    "esm_plausibility": 0.9411,
    "developability": {
      "max_own_aggregation_score": 0.5764,
      "percentile_vs_reference_windows": 37.5,
      "max_allowed_percentile": 40,
      "scoring_basis": "exposed_windows_only",
      "n_cysteines": 0,
      "cysteine_check_passed": true,
      "developability_passed": true
    },
    "hydrophobic_core_consistency": {
      "n_residues": 60,
      "pearson_r": -0.5262,
      "pearson_p": 1.6e-05,
      "well_packed": true,
      "rel_sasa_by_resid": {
        "1": 0.8337,
        "2": 0.7483,
        "3": 0.7219,
        "4": 0.4581,
        "5": 0.662,
        "6": 0.3117,
        "7": 0.666,
        "8": 0.6111,
        "9": 0.2817,
        "10": 0.1014,
        "11": 0.4583,
        "12": 0.7054,
        "13": 0.213,
        "14": 0.1915,
        "15": 0.6883,
        "16": 0.3751,
        "17": 0.1256,
        "18": 0.4372,
        "19": 0.3695,
        "20": 0.3839,
        "21": 0.7742,
        "22": 0.351,
        "23": 0.2087,
        "24": 0.6206,
        "25": 0.5269,
        "26": 0.6575,
        "27": 0.5879,
        "28": 0.1145,
        "29": 0.2761,
        "30": 0.1754,
        "31": 0.3672,
        "32": 0.0796,
        "33": 0.5037,
        "34": 0.358,
        "35": 0.0224,
        "36": 0.5797,
        "37": 0.7042,
        "38": 0.464,
        "39": 0.5423,
        "40": 0.7011,
        "41": 0.4455,
        "42": 0.1248,
        "43": 0.3844,
        "44": 0.7216,
        "45": 0.1365,
        "46": 0.1801,
        "47": 0.5936,
        "48": 0.474,
        "49": 0.0363,
        "50": 0.4858,
        "51": 0.4637,
        "52": 0.5454,
        "53": 0.0582,
        "54": 0.5764,
        "55": 0.5218,
        "56": 0.5484,
        "57": 0.1814,
        "58": 0.4899,
        "59": 0.7934,
        "60": 1.0366
      }
    },
    "chemical_complementarity": {
      "n_chemical_contacts": 201,
      "hydrophobic_complementarity": 0.6474,
      "charge_complementarity": -0.0697
    },
    "composite_score": 0.4248,
    "selectivity_margin": 0.0058,
    "individually_significant": false
  },
  {
    "design_id": "r1_c0_scaffold_protA_bdomain_s0",
    "backbone_id": "r1_c0_scaffold_protA_bdomain",
    "params": {
      "topology": "scaffold_protA_bdomain",
      "standoff_A": 9.606602865105216,
      "mpnn_temperature": 0.15,
      "hotspot_fraction": 0.734777905637904
    },
    "sequence": "ASAAAAAKGAAAGLAAARTLPALPPEELQALLAAAEADPSGAQAALAQARALAAARAPPA",
    "mpnn_score": 1.1727,
    "geometric": {
      "n_clashes": 25,
      "n_contacts": 454,
      "n_hbond_candidates": 13,
      "clash_score": 0.0833,
      "packing_density_sc_proxy": 0.1591,
      "mean_contacts_per_atom": 1.513
    },
    "esm_plausibility": 0.9402,
    "developability": {
      "max_own_aggregation_score": 0.6016,
      "percentile_vs_reference_windows": 37.5,
      "max_allowed_percentile": 40,
      "scoring_basis": "exposed_windows_only",
      "n_cysteines": 0,
      "cysteine_check_passed": true,
      "developability_passed": true
    },
    "hydrophobic_core_consistency": {
      "n_residues": 60,
      "pearson_r": -0.3723,
      "pearson_p": 0.0034,
      "well_packed": true,
      "rel_sasa_by_resid": {
        "1": 1.1285,
        "2": 0.7771,
        "3": 0.7952,
        "4": 0.7727,
        "5": 0.7822,
        "6": 0.6154,
        "7": 0.4882,
        "8": 0.8873,
        "9": 0.2748,
        "10": 0.0881,
        "11": 0.4237,
        "12": 0.6999,
        "13": 0.2333,
        "14": 0.246,
        "15": 0.6638,
        "16": 0.4759,
        "17": 0.166,
        "18": 0.5788,
        "19": 0.4839,
        "20": 0.2841,
        "21": 0.7876,
        "22": 0.3637,
        "23": 0.24,
        "24": 0.5456,
        "25": 0.4553,
        "26": 0.6095,
        "27": 0.6411,
        "28": 0.051,
        "29": 0.3535,
        "30": 0.4494,
        "31": 0.2053,
        "32": 0.1416,
        "33": 0.4641,
        "34": 0.347,
        "35": 0.0064,
        "36": 0.6576,
        "37": 0.7429,
        "38": 0.4091,
        "39": 0.5221,
        "40": 0.7123,
        "41": 0.4881,
        "42": 0.0998,
        "43": 0.4733,
        "44": 0.5439,
        "45": 0.1762,
        "46": 0.1442,
        "47": 0.5202,
        "48": 0.4209,
        "49": 0.0508,
        "50": 0.5758,
        "51": 0.5441,
        "52": 0.4042,
        "53": 0.0012,
        "54": 0.4343,
        "55": 0.7054,
        "56": 0.5469,
        "57": 0.1665,
        "58": 0.5496,
        "59": 0.7885,
        "60": 0.6148
      }
    },
    "chemical_complementarity": {
      "n_chemical_contacts": 135,
      "hydrophobic_complementarity": -0.0494,
      "charge_complementarity": -0.0296
    },
    "composite_score": 0.4185,
    "selectivity_margin": 0.0049,
    "individually_significant": false
  },
  {
    "design_id": "r0_c3_long_helix_capper_s2",
    "backbone_id": "r0_c3_long_helix_capper",
    "params": {
      "topology": "long_helix_capper",
      "standoff_A": 13.58209290616664,
      "mpnn_temperature": 0.15,
      "hotspot_fraction": 0.6136193608923884
    },
    "sequence": "KAKEEEEKKEEEEKKKKEEEKKKKEEEEKKKKEEEKKKKEEEKKKKEEEKKKEEKKKKEEEKKKK",
    "mpnn_score": 0.9816,
    "geometric": {
      "n_clashes": 8,
      "n_contacts": 158,
      "n_hbond_candidates": 7,
      "clash_score": 0.0246,
      "packing_density_sc_proxy": 0.0573,
      "mean_contacts_per_atom": 0.486
    },
    "esm_plausibility": 0.9431,
    "developability": {
      "max_own_aggregation_score": 0.0,
      "percentile_vs_reference_windows": 12.5,
      "max_allowed_percentile": 40,
      "scoring_basis": "exposed_windows_only",
      "n_cysteines": 0,
      "cysteine_check_passed": true,
      "developability_passed": true
    },
    "hydrophobic_core_consistency": {
      "n_residues": 65,
      "pearson_r": -0.077,
      "pearson_p": 0.542079,
      "well_packed": false,
      "rel_sasa_by_resid": {
        "1": 0.8888,
        "2": 0.6704,
        "3": 0.7452,
        "4": 0.5243,
        "5": 0.5793,
        "6": 0.5803,
        "7": 0.6235,
        "8": 0.5902,
        "9": 0.6148,
        "10": 0.5755,
        "11": 0.5105,
        "12": 0.5187,
        "13": 0.5648,
        "14": 0.645,
        "15": 0.599,
        "16": 0.5966,
        "17": 0.5687,
        "18": 0.5173,
        "19": 0.5156,
        "20": 0.4959,
        "21": 0.6882,
        "22": 0.5991,
        "23": 0.6038,
        "24": 0.5911,
        "25": 0.5145,
        "26": 0.5181,
        "27": 0.5172,
        "28": 0.5667,
        "29": 0.643,
        "30": 0.6036,
        "31": 0.5987,
        "32": 0.571,
        "33": 0.5186,
        "34": 0.5158,
        "35": 0.4983,
        "36": 0.6818,
        "37": 0.5974,
        "38": 0.5999,
        "39": 0.5674,
        "40": 0.516,
        "41": 0.5162,
        "42": 0.4967,
        "43": 0.6918,
        "44": 0.6027,
        "45": 0.5929,
        "46": 0.57,
        "47": 0.517,
        "48": 0.513,
        "49": 0.5571,
        "50": 0.6432,
        "51": 0.5819,
        "52": 0.6446,
        "53": 0.5116,
        "54": 0.4931,
        "55": 0.6606,
        "56": 0.6405,
        "57": 0.6013,
        "58": 0.5752,
        "59": 0.5132,
        "60": 0.5193,
        "61": 0.494,
        "62": 0.7172,
        "63": 0.7503,
        "64": 0.7635,
        "65": 0.8865
      }
    },
    "chemical_complementarity": {
      "n_chemical_contacts": 42,
      "hydrophobic_complementarity": 5.8221,
      "charge_complementarity": -0.0714
    },
    "composite_score": 0.4845,
    "selectivity_margin": 0.0048,
    "individually_significant": false
  },
  {
    "design_id": "r0_c3_long_helix_capper_s1",
    "backbone_id": "r0_c3_long_helix_capper",
    "params": {
      "topology": "long_helix_capper",
      "standoff_A": 13.58209290616664,
      "mpnn_temperature": 0.15,
      "hotspot_fraction": 0.6136193608923884
    },
    "sequence": "EKEKEEKEKEKKKEEKEKEEEKKKKEEEEKKKEEEEKKKKEEEEKKKEEEERKKEEEEKEKKAKE",
    "mpnn_score": 1.0909,
    "geometric": {
      "n_clashes": 8,
      "n_contacts": 158,
      "n_hbond_candidates": 7,
      "clash_score": 0.0246,
      "packing_density_sc_proxy": 0.0573,
      "mean_contacts_per_atom": 0.486
    },
    "esm_plausibility": 0.9475,
    "developability": {
      "max_own_aggregation_score": 0.002,
      "percentile_vs_reference_windows": 12.5,
      "max_allowed_percentile": 40,
      "scoring_basis": "exposed_windows_only",
      "n_cysteines": 0,
      "cysteine_check_passed": true,
      "developability_passed": true
    },
    "hydrophobic_core_consistency": {
      "n_residues": 65,
      "pearson_r": 0.0275,
      "pearson_p": 0.827781,
      "well_packed": false,
      "rel_sasa_by_resid": {
        "1": 0.8765,
        "2": 0.7523,
        "3": 0.6349,
        "4": 0.736,
        "5": 0.499,
        "6": 0.6252,
        "7": 0.5614,
        "8": 0.5629,
        "9": 0.6297,
        "10": 0.549,
        "11": 0.6554,
        "12": 0.5642,
        "13": 0.7105,
        "14": 0.4952,
        "15": 0.5604,
        "16": 0.6276,
        "17": 0.6172,
        "18": 0.5848,
        "19": 0.5027,
        "20": 0.5747,
        "21": 0.4868,
        "22": 0.6872,
        "23": 0.6096,
        "24": 0.6064,
        "25": 0.5941,
        "26": 0.5139,
        "27": 0.5166,
        "28": 0.5119,
        "29": 0.6228,
        "30": 0.598,
        "31": 0.6021,
        "32": 0.6178,
        "33": 0.5003,
        "34": 0.5153,
        "35": 0.5168,
        "36": 0.563,
        "37": 0.6413,
        "38": 0.603,
        "39": 0.5986,
        "40": 0.5973,
        "41": 0.5137,
        "42": 0.5144,
        "43": 0.5109,
        "44": 0.6182,
        "45": 0.5877,
        "46": 0.6003,
        "47": 0.6194,
        "48": 0.5671,
        "49": 0.4761,
        "50": 0.5184,
        "51": 0.6488,
        "52": 0.5765,
        "53": 0.5741,
        "54": 0.6152,
        "55": 0.568,
        "56": 0.4783,
        "57": 0.5112,
        "58": 0.563,
        "59": 0.6535,
        "60": 0.55,
        "61": 0.6459,
        "62": 0.6198,
        "63": 0.6859,
        "64": 0.744,
        "65": 0.8422
      }
    },
    "chemical_complementarity": {
      "n_chemical_contacts": 42,
      "hydrophobic_complementarity": 5.7145,
      "charge_complementarity": -0.0714
    },
    "composite_score": 0.4771,
    "selectivity_margin": 0.0045,
    "individually_significant": false
  },
  {
    "design_id": "r3_c3_helix_hairpin_s2",
    "backbone_id": "r3_c3_helix_hairpin",
    "params": {
      "topology": "helix_hairpin",
      "standoff_A": 10.146415069594463,
      "mpnn_temperature": 0.2,
      "hotspot_fraction": 0.84437610637996
    },
    "sequence": "EAFLEEFERELKEEEEERKKELEKRKEELKKKKEEEEELKKLREEEEKFAKELEERLRKLKELL",
    "mpnn_score": 1.398,
    "geometric": {
      "n_clashes": 31,
      "n_contacts": 363,
      "n_hbond_candidates": 14,
      "clash_score": 0.0969,
      "packing_density_sc_proxy": 0.1242,
      "mean_contacts_per_atom": 1.134
    },
    "esm_plausibility": 0.9395,
    "developability": {
      "max_own_aggregation_score": 0.5816,
      "percentile_vs_reference_windows": 37.5,
      "max_allowed_percentile": 40,
      "scoring_basis": "exposed_windows_only",
      "n_cysteines": 0,
      "cysteine_check_passed": true,
      "developability_passed": true
    },
    "hydrophobic_core_consistency": {
      "n_residues": 64,
      "pearson_r": -0.3902,
      "pearson_p": 0.001434,
      "well_packed": true,
      "rel_sasa_by_resid": {
        "1": 0.8084,
        "2": 0.606,
        "3": 0.6259,
        "4": 0.2488,
        "5": 0.6053,
        "6": 0.48,
        "7": 0.303,
        "8": 0.3942,
        "9": 0.5924,
        "10": 0.5441,
        "11": 0.1749,
        "12": 0.683,
        "13": 0.5594,
        "14": 0.4857,
        "15": 0.3048,
        "16": 0.6382,
        "17": 0.4367,
        "18": 0.1638,
        "19": 0.5133,
        "20": 0.5008,
        "21": 0.4942,
        "22": 0.242,
        "23": 0.402,
        "24": 0.5769,
        "25": 0.5927,
        "26": 0.3913,
        "27": 0.5737,
        "28": 0.591,
        "29": 0.0037,
        "30": 0.487,
        "31": 0.4967,
        "32": 0.2593,
        "33": 0.3232,
        "34": 0.2794,
        "35": 0.226,
        "36": 0.4724,
        "37": 0.5797,
        "38": 0.4295,
        "39": 0.1627,
        "40": 0.488,
        "41": 0.6811,
        "42": 0.372,
        "43": 0.7107,
        "44": 0.4857,
        "45": 0.5495,
        "46": 0.2888,
        "47": 0.5662,
        "48": 0.5437,
        "49": 0.3246,
        "50": 0.3379,
        "51": 0.6392,
        "52": 0.5391,
        "53": 0.1743,
        "54": 0.3835,
        "55": 0.4842,
        "56": 0.2756,
        "57": 0.3363,
        "58": 0.6116,
        "59": 0.5008,
        "60": 0.1379,
        "61": 0.5866,
        "62": 0.6616,
        "63": 0.7755,
        "64": 0.7533
      }
    },
    "chemical_complementarity": {
      "n_chemical_contacts": 104,
      "hydrophobic_complementarity": 3.6088,
      "charge_complementarity": 0.0481
    },
    "composite_score": 0.483,
    "selectivity_margin": 0.0044,
    "individually_significant": false
  },
  {
    "design_id": "r6_c4_three_helix_bundle_s1",
    "backbone_id": "r6_c4_three_helix_bundle",
    "params": {
      "topology": "three_helix_bundle",
      "standoff_A": 14.70752069201864,
      "mpnn_temperature": 0.2,
      "hotspot_fraction": 0.8222409203253404
    },
    "sequence": "KEGLDKVKKIVEEAKEWVKKIVKGGGGGAKEAEKKLKEFKEKAEKALKEGEGDKEEVQKGKELVKKAVEEFKKAVKEL",
    "mpnn_score": 1.1145,
    "geometric": {
      "n_clashes": 29,
      "n_contacts": 573,
      "n_hbond_candidates": 24,
      "clash_score": 0.0744,
      "packing_density_sc_proxy": 0.1552,
      "mean_contacts_per_atom": 1.469
    },
    "esm_plausibility": 0.9382,
    "developability": {
      "max_own_aggregation_score": 0.5509,
      "percentile_vs_reference_windows": 37.5,
      "max_allowed_percentile": 40,
      "scoring_basis": "exposed_windows_only",
      "n_cysteines": 0,
      "cysteine_check_passed": true,
      "developability_passed": true
    },
    "hydrophobic_core_consistency": {
      "n_residues": 78,
      "pearson_r": -0.6341,
      "pearson_p": 0.0,
      "well_packed": true,
      "rel_sasa_by_resid": {
        "1": 0.7419,
        "2": 0.6791,
        "3": 0.2634,
        "4": 0.1398,
        "5": 0.3818,
        "6": 0.5719,
        "7": 0.0178,
        "8": 0.4707,
        "9": 0.6077,
        "10": 0.2907,
        "11": 0.0786,
        "12": 0.5517,
        "13": 0.5154,
        "14": 0.0626,
        "15": 0.095,
        "16": 0.408,
        "17": 0.3188,
        "18": 0.0504,
        "19": 0.5634,
        "20": 0.5937,
        "21": 0.1224,
        "22": 0.2532,
        "23": 0.8303,
        "24": 0.7365,
        "25": 0.4009,
        "26": 0.4106,
        "27": 0.4424,
        "28": 0.6461,
        "29": 0.3926,
        "30": 0.6355,
        "31": 0.5442,
        "32": 0.0449,
        "33": 0.2208,
        "34": 0.5331,
        "35": 0.3371,
        "36": 0.0909,
        "37": 0.3544,
        "38": 0.4054,
        "39": 0.145,
        "40": 0.088,
        "41": 0.3496,
        "42": 0.5638,
        "43": 0.0188,
        "44": 0.3189,
        "45": 0.6371,
        "46": 0.2956,
        "47": 0.0652,
        "48": 0.6526,
        "49": 0.6691,
        "50": 0.3669,
        "51": 0.4602,
        "52": 0.279,
        "53": 0.4654,
        "54": 0.2713,
        "55": 0.5611,
        "56": 0.2322,
        "57": 0.1273,
        "58": 0.5257,
        "59": 0.623,
        "60": 0.0198,
        "61": 0.3257,
        "62": 0.5951,
        "63": 0.513,
        "64": 0.0354,
        "65": 0.4237,
        "66": 0.6081,
        "67": 0.1508,
        "68": 0.1871,
        "69": 0.3861,
        "70": 0.526,
        "71": 0.0381,
        "72": 0.318,
        "73": 0.5827,
        "74": 0.2351,
        "75": 0.2129,
        "76": 0.5878,
        "77": 0.5446,
        "78": 0.6201
      }
    },
    "chemical_complementarity": {
      "n_chemical_contacts": 166,
      "hydrophobic_complementarity": 1.2725,
      "charge_complementarity": 0.0
    },
    "composite_score": 0.4657,
    "selectivity_margin": 0.0037,
    "individually_significant": false
  },
  {
    "design_id": "r3_c3_helix_hairpin_s3",
    "backbone_id": "r3_c3_helix_hairpin",
    "params": {
      "topology": "helix_hairpin",
      "standoff_A": 10.146415069594463,
      "mpnn_temperature": 0.2,
      "hotspot_fraction": 0.84437610637996
    },
    "sequence": "EEELKEFQKKLEEKKEELEKELKEIEKELAKGALEEEKKKKLEEKKKEFKKELEEELEKLKKKL",
    "mpnn_score": 1.2406,
    "geometric": {
      "n_clashes": 31,
      "n_contacts": 363,
      "n_hbond_candidates": 14,
      "clash_score": 0.0969,
      "packing_density_sc_proxy": 0.1242,
      "mean_contacts_per_atom": 1.134
    },
    "esm_plausibility": 0.9431,
    "developability": {
      "max_own_aggregation_score": 0.4381,
      "percentile_vs_reference_windows": 12.5,
      "max_allowed_percentile": 40,
      "scoring_basis": "exposed_windows_only",
      "n_cysteines": 0,
      "cysteine_check_passed": true,
      "developability_passed": true
    },
    "hydrophobic_core_consistency": {
      "n_residues": 64,
      "pearson_r": -0.673,
      "pearson_p": 0.0,
      "well_packed": true,
      "rel_sasa_by_resid": {
        "1": 0.6954,
        "2": 0.7114,
        "3": 0.7043,
        "4": 0.3244,
        "5": 0.5149,
        "6": 0.5567,
        "7": 0.1681,
        "8": 0.3396,
        "9": 0.619,
        "10": 0.6154,
        "11": 0.268,
        "12": 0.5565,
        "13": 0.5706,
        "14": 0.5912,
        "15": 0.1899,
        "16": 0.5396,
        "17": 0.5595,
        "18": 0.2401,
        "19": 0.4566,
        "20": 0.6508,
        "21": 0.5737,
        "22": 0.2748,
        "23": 0.561,
        "24": 0.6337,
        "25": 0.297,
        "26": 0.2734,
        "27": 0.7243,
        "28": 0.7099,
        "29": 0.1195,
        "30": 0.4731,
        "31": 0.5008,
        "32": 0.2572,
        "33": 0.3105,
        "34": 0.2529,
        "35": 0.3787,
        "36": 0.6385,
        "37": 0.6243,
        "38": 0.5751,
        "39": 0.3112,
        "40": 0.6172,
        "41": 0.5922,
        "42": 0.1825,
        "43": 0.5039,
        "44": 0.5732,
        "45": 0.6751,
        "46": 0.2039,
        "47": 0.6224,
        "48": 0.5746,
        "49": 0.2066,
        "50": 0.5066,
        "51": 0.6776,
        "52": 0.6125,
        "53": 0.1837,
        "54": 0.4854,
        "55": 0.5632,
        "56": 0.4798,
        "57": 0.3927,
        "58": 0.5243,
        "59": 0.6285,
        "60": 0.277,
        "61": 0.6245,
        "62": 0.7211,
        "63": 0.8286,
        "64": 0.6606
      }
    },
    "chemical_complementarity": {
      "n_chemical_contacts": 104,
      "hydrophobic_complementarity": 3.2858,
      "charge_complementarity": 0.0481
    },
    "composite_score": 0.4981,
    "selectivity_margin": 0.0035,
    "individually_significant": false
  },
  {
    "design_id": "r6_c4_three_helix_bundle_s0",
    "backbone_id": "r6_c4_three_helix_bundle",
    "params": {
      "topology": "three_helix_bundle",
      "standoff_A": 14.70752069201864,
      "mpnn_temperature": 0.2,
      "hotspot_fraction": 0.8222409203253404
    },
    "sequence": "DEARERAREIVERARRRVEEWVRGGRGGREEFLREIERFREEGERALEEGRGEEEEVEEARREIEEVVREAEEALRRL",
    "mpnn_score": 1.0122,
    "geometric": {
      "n_clashes": 29,
      "n_contacts": 573,
      "n_hbond_candidates": 24,
      "clash_score": 0.0744,
      "packing_density_sc_proxy": 0.1552,
      "mean_contacts_per_atom": 1.469
    },
    "esm_plausibility": 0.9396,
    "developability": {
      "max_own_aggregation_score": 0.5334,
      "percentile_vs_reference_windows": 37.5,
      "max_allowed_percentile": 40,
      "scoring_basis": "exposed_windows_only",
      "n_cysteines": 0,
      "cysteine_check_passed": true,
      "developability_passed": true
    },
    "hydrophobic_core_consistency": {
      "n_residues": 78,
      "pearson_r": -0.7165,
      "pearson_p": 0.0,
      "well_packed": true,
      "rel_sasa_by_resid": {
        "1": 0.4762,
        "2": 0.7337,
        "3": 0.1716,
        "4": 0.2352,
        "5": 0.5969,
        "6": 0.457,
        "7": 0.0024,
        "8": 0.4697,
        "9": 0.643,
        "10": 0.0865,
        "11": 0.0396,
        "12": 0.491,
        "13": 0.6598,
        "14": 0.091,
        "15": 0.4748,
        "16": 0.6189,
        "17": 0.4101,
        "18": 0.1023,
        "19": 0.4861,
        "20": 0.5102,
        "21": 0.037,
        "22": 0.3266,
        "23": 0.7652,
        "24": 0.6599,
        "25": 0.3619,
        "26": 0.3409,
        "27": 0.3125,
        "28": 0.6348,
        "29": 0.4076,
        "30": 0.6191,
        "31": 0.6121,
        "32": 0.06,
        "33": 0.3434,
        "34": 0.6635,
        "35": 0.3765,
        "36": 0.1124,
        "37": 0.598,
        "38": 0.6039,
        "39": 0.1689,
        "40": 0.1761,
        "41": 0.6293,
        "42": 0.4034,
        "43": 0.0,
        "44": 0.3558,
        "45": 0.607,
        "46": 0.1233,
        "47": 0.0585,
        "48": 0.622,
        "49": 0.6336,
        "50": 0.2517,
        "51": 0.6693,
        "52": 0.2309,
        "53": 0.19,
        "54": 0.6049,
        "55": 0.6658,
        "56": 0.2314,
        "57": 0.175,
        "58": 0.6079,
        "59": 0.4934,
        "60": 0.038,
        "61": 0.3115,
        "62": 0.598,
        "63": 0.3934,
        "64": 0.0413,
        "65": 0.4165,
        "66": 0.5114,
        "67": 0.1457,
        "68": 0.213,
        "69": 0.5976,
        "70": 0.5655,
        "71": 0.0299,
        "72": 0.3543,
        "73": 0.5063,
        "74": 0.2857,
        "75": 0.0359,
        "76": 0.6996,
        "77": 0.7542,
        "78": 0.4932
      }
    },
    "chemical_complementarity": {
      "n_chemical_contacts": 166,
      "hydrophobic_complementarity": 1.1441,
      "charge_complementarity": 0.0422
    },
    "composite_score": 0.4703,
    "selectivity_margin": 0.0026,
    "individually_significant": false
  },
  {
    "design_id": "r9_c7_scaffold_engrailed_hd_s1",
    "backbone_id": "r9_c7_scaffold_engrailed_hd",
    "params": {
      "topology": "scaffold_engrailed_hd",
      "standoff_A": 11.426377890599023,
      "mpnn_temperature": 0.2,
      "hotspot_fraction": 0.7742121959113497
    },
    "sequence": "PPPITLSEEQLAILDARFAENPYLSPEELKQLSEELGLPESQIRQWFERRRAEA",
    "mpnn_score": 1.1167,
    "geometric": {
      "n_clashes": 32,
      "n_contacts": 447,
      "n_hbond_candidates": 16,
      "clash_score": 0.1185,
      "packing_density_sc_proxy": 0.1715,
      "mean_contacts_per_atom": 1.656
    },
    "esm_plausibility": 0.9358,
    "developability": {
      "max_own_aggregation_score": 0.5802,
      "percentile_vs_reference_windows": 37.5,
      "max_allowed_percentile": 40,
      "scoring_basis": "exposed_windows_only",
      "n_cysteines": 0,
      "cysteine_check_passed": true,
      "developability_passed": true
    },
    "hydrophobic_core_consistency": {
      "n_residues": 54,
      "pearson_r": -0.3068,
      "pearson_p": 0.024052,
      "well_packed": true,
      "rel_sasa_by_resid": {
        "1": 0.9699,
        "2": 0.5819,
        "3": 0.4264,
        "4": 0.4727,
        "5": 0.8063,
        "6": 0.1695,
        "7": 0.4261,
        "8": 0.6449,
        "9": 0.6361,
        "10": 0.2054,
        "11": 0.2975,
        "12": 0.5165,
        "13": 0.575,
        "14": 0.0784,
        "15": 0.2697,
        "16": 0.572,
        "17": 0.2208,
        "18": 0.1872,
        "19": 0.595,
        "20": 0.6584,
        "21": 0.3994,
        "22": 0.3259,
        "23": 0.5572,
        "24": 0.0847,
        "25": 0.5026,
        "26": 0.5855,
        "27": 0.6609,
        "28": 0.4067,
        "29": 0.0859,
        "30": 0.4378,
        "31": 0.3109,
        "32": 0.2535,
        "33": 0.0174,
        "34": 0.6576,
        "35": 0.6587,
        "36": 0.1382,
        "37": 0.5808,
        "38": 0.1475,
        "39": 0.4811,
        "40": 0.0281,
        "41": 0.6077,
        "42": 0.1012,
        "43": 0.0536,
        "44": 0.4532,
        "45": 0.3321,
        "46": 0.2055,
        "47": 0.0533,
        "48": 0.4398,
        "49": 0.6504,
        "50": 0.427,
        "51": 0.4313,
        "52": 0.7,
        "53": 0.5376,
        "54": 0.7456
      }
    },
    "chemical_complementarity": {
      "n_chemical_contacts": 130,
      "hydrophobic_complementarity": 1.1347,
      "charge_complementarity": -0.0154
    },
    "composite_score": 0.4332,
    "selectivity_margin": 0.0024,
    "individually_significant": false
  },
  {
    "design_id": "r0_c5_scaffold_de_novo_3helix_s2",
    "backbone_id": "r0_c5_scaffold_de_novo_3helix",
    "params": {
      "topology": "scaffold_de_novo_3helix",
      "standoff_A": 12.05331519297652,
      "mpnn_temperature": 0.2,
      "hotspot_fraction": 0.6772629840649342
    },
    "sequence": "MSEEQIKEELKKFEEKLKEFEKKLKELGDNKEKYKPFIEELEKFEEEIEKFIEEIKKYIEQGHPEFEEYKKKAEELRKKVKEIKEKLKKEREG",
    "mpnn_score": 0.996,
    "geometric": {
      "n_clashes": 68,
      "n_contacts": 982,
      "n_hbond_candidates": 41,
      "clash_score": 0.1462,
      "packing_density_sc_proxy": 0.2088,
      "mean_contacts_per_atom": 2.112
    },
    "esm_plausibility": 0.9411,
    "developability": {
      "max_own_aggregation_score": 0.5056,
      "percentile_vs_reference_windows": 37.5,
      "max_allowed_percentile": 40,
      "scoring_basis": "exposed_windows_only",
      "n_cysteines": 0,
      "cysteine_check_passed": true,
      "developability_passed": true
    },
    "hydrophobic_core_consistency": {
      "n_residues": 93,
      "pearson_r": -0.6531,
      "pearson_p": 0.0,
      "well_packed": true,
      "rel_sasa_by_resid": {
        "1": 0.4563,
        "2": 0.4108,
        "3": 0.3639,
        "4": 0.6985,
        "5": 0.5419,
        "6": 0.0085,
        "7": 0.3715,
        "8": 0.5544,
        "9": 0.5586,
        "10": 0.0464,
        "11": 0.563,
        "12": 0.6357,
        "13": 0.069,
        "14": 0.2511,
        "15": 0.5835,
        "16": 0.5953,
        "17": 0.0973,
        "18": 0.6079,
        "19": 0.4591,
        "20": 0.0447,
        "21": 0.3731,
        "22": 0.7369,
        "23": 0.4698,
        "24": 0.1872,
        "25": 0.8027,
        "26": 0.6295,
        "27": 0.2615,
        "28": 0.4739,
        "29": 0.7521,
        "30": 0.5573,
        "31": 0.3482,
        "32": 0.5746,
        "33": 0.7066,
        "34": 0.0707,
        "35": 0.2935,
        "36": 0.6208,
        "37": 0.2408,
        "38": 0.0486,
        "39": 0.5185,
        "40": 0.632,
        "41": 0.0511,
        "42": 0.4037,
        "43": 0.6466,
        "44": 0.2218,
        "45": 0.0146,
        "46": 0.4442,
        "47": 0.6523,
        "48": 0.0192,
        "49": 0.2916,
        "50": 0.6349,
        "51": 0.158,
        "52": 0.0781,
        "53": 0.4745,
        "54": 0.4699,
        "55": 0.0044,
        "56": 0.425,
        "57": 0.606,
        "58": 0.2734,
        "59": 0.1124,
        "60": 0.6104,
        "61": 0.7571,
        "62": 0.5658,
        "63": 0.5101,
        "64": 0.6484,
        "65": 0.695,
        "66": 0.0388,
        "67": 0.28,
        "68": 0.5977,
        "69": 0.2235,
        "70": 0.0252,
        "71": 0.5882,
        "72": 0.5924,
        "73": 0.0151,
        "74": 0.2299,
        "75": 0.5234,
        "76": 0.1731,
        "77": 0.1323,
        "78": 0.579,
        "79": 0.625,
        "80": 0.0253,
        "81": 0.187,
        "82": 0.5646,
        "83": 0.2245,
        "84": 0.0222,
        "85": 0.5368,
        "86": 0.6703,
        "87": 0.1739,
        "88": 0.3105,
        "89": 0.6125,
        "90": 0.5019,
        "91": 0.2177,
        "92": 0.6682,
        "93": 0.8709
      }
    },
    "chemical_complementarity": {
      "n_chemical_contacts": 252,
      "hydrophobic_complementarity": 1.5525,
      "charge_complementarity": 0.0159
    },
    "composite_score": 0.4724,
    "selectivity_margin": 0.0015,
    "individually_significant": false
  },
  {
    "design_id": "r9_c7_scaffold_engrailed_hd_s3",
    "backbone_id": "r9_c7_scaffold_engrailed_hd",
    "params": {
      "topology": "scaffold_engrailed_hd",
      "standoff_A": 11.426377890599023,
      "mpnn_temperature": 0.2,
      "hotspot_fraction": 0.7742121959113497
    },
    "sequence": "MPAIELSEEQLAALEREFARNPELSPEELKRLSEELGLPPEQIRAWFERRRAEA",
    "mpnn_score": 1.1071,
    "geometric": {
      "n_clashes": 32,
      "n_contacts": 447,
      "n_hbond_candidates": 16,
      "clash_score": 0.1185,
      "packing_density_sc_proxy": 0.1715,
      "mean_contacts_per_atom": 1.656
    },
    "esm_plausibility": 0.9433,
    "developability": {
      "max_own_aggregation_score": 0.5468,
      "percentile_vs_reference_windows": 37.5,
      "max_allowed_percentile": 40,
      "scoring_basis": "exposed_windows_only",
      "n_cysteines": 0,
      "cysteine_check_passed": true,
      "developability_passed": true
    },
    "hydrophobic_core_consistency": {
      "n_residues": 54,
      "pearson_r": -0.4894,
      "pearson_p": 0.000173,
      "well_packed": true,
      "rel_sasa_by_resid": {
        "1": 0.7443,
        "2": 0.4037,
        "3": 0.5092,
        "4": 0.4854,
        "5": 0.7704,
        "6": 0.2186,
        "7": 0.503,
        "8": 0.5421,
        "9": 0.6164,
        "10": 0.2954,
        "11": 0.2693,
        "12": 0.4548,
        "13": 0.352,
        "14": 0.0705,
        "15": 0.4351,
        "16": 0.6212,
        "17": 0.2553,
        "18": 0.087,
        "19": 0.7194,
        "20": 0.67,
        "21": 0.4748,
        "22": 0.358,
        "23": 0.5608,
        "24": 0.1135,
        "25": 0.2941,
        "26": 0.6487,
        "27": 0.656,
        "28": 0.4367,
        "29": 0.0245,
        "30": 0.5488,
        "31": 0.72,
        "32": 0.2449,
        "33": 0.0269,
        "34": 0.6593,
        "35": 0.6494,
        "36": 0.225,
        "37": 0.6475,
        "38": 0.1176,
        "39": 0.4009,
        "40": 0.1706,
        "41": 0.4292,
        "42": 0.1283,
        "43": 0.1119,
        "44": 0.5011,
        "45": 0.382,
        "46": 0.0993,
        "47": 0.0184,
        "48": 0.4783,
        "49": 0.6399,
        "50": 0.3104,
        "51": 0.5659,
        "52": 0.6905,
        "53": 0.6257,
        "54": 0.6551
      }
    },
    "chemical_complementarity": {
      "n_chemical_contacts": 130,
      "hydrophobic_complementarity": 0.4895,
      "charge_complementarity": -0.0231
    },
    "composite_score": 0.4345,
    "selectivity_margin": 0.0015,
    "individually_significant": false
  }
]